README.md
setup.cfg
setup.py
constants/__init__.py
constants/templates.py
exception/__init__.py
exception/argument_empty_exception.py
exception/argument_exception.py
exception/argument_not_equal_exception.py
exception/argument_not_instance_of_exception.py
exception/argument_not_null_exception.py
exception/argument_null_exception.py
exception/argument_out_of_range_exception.py
exception/base_exception.py
exception/no_such_element_exception.py
guard/__init__.py
guard/configurations.py
guard/guard_compare.py
guard/guard_float.py
guard/guard_instance.py
guard/guard_iterable.py
guard/guard_null.py
guard/guard_numeric.py
guard/guard_string.py
python_parameter_guard.egg-info/PKG-INFO
python_parameter_guard.egg-info/SOURCES.txt
python_parameter_guard.egg-info/dependency_links.txt
python_parameter_guard.egg-info/requires.txt
python_parameter_guard.egg-info/top_level.txt
tests/__init__.py
tests/test_guard_compare.py
tests/test_guard_float.py
tests/test_guard_instance.py
tests/test_guard_iterable.py
tests/test_guard_null.py
tests/test_guard_numeric.py
tests/test_guard_string.py