Metadata-Version: 2.1
Name: python-parameter-guard
Version: 0.1.0
Summary: Guard is a fluent argument validation library that is intuitive, fast and extensible.
Home-page: https://github.com/joaoteixeira88/python-guard
Author: Joao Teixeira
Author-email: ervilhaman@hotmail.com
License: MIT
Download-URL: https://github.com/joaoteixeira88/python-guard/archive/0.1.0.tar.gz
Keywords: python,guard,parameters,exceptions
Platform: UNKNOWN
Classifier: Development Status :: 3 - Alpha
Classifier: Intended Audience :: Developers
Classifier: Topic :: Software Development :: Build Tools
Classifier: License :: OSI Approved :: MIT License
Classifier: Programming Language :: Python :: 3
Classifier: Programming Language :: Python :: 3.4
Classifier: Programming Language :: Python :: 3.5
Classifier: Programming Language :: Python :: 3.6
Requires-Python: >3.0
